MANIFEST.in
README.rst
setup.py
pyside_tooltip/__init__.py
pyside_tooltip/tooltip.py
pyside_tooltip/tooltipAlignment.py
pyside_tooltip/tooltipWithArrow.py
pyside_tooltip.egg-info/PKG-INFO
pyside_tooltip.egg-info/SOURCES.txt
pyside_tooltip.egg-info/dependency_links.txt
pyside_tooltip.egg-info/not-zip-safe
pyside_tooltip.egg-info/requires.txt
pyside_tooltip.egg-info/top_level.txt
pyside_tooltip/positioning/__init__.py
pyside_tooltip/positioning/bottomTooltipPositioning.py
pyside_tooltip/positioning/bottomTooltipPositioningWithArrow.py
pyside_tooltip/positioning/leftTooltipPositioning.py
pyside_tooltip/positioning/leftTooltipPositioningWithArrow.py
pyside_tooltip/positioning/nullTooltipPositioning.py
pyside_tooltip/positioning/rightTooltipPositioning.py
pyside_tooltip/positioning/rightTooltipPositioningWithArrow.py
pyside_tooltip/positioning/tooltipPositioning.py
pyside_tooltip/positioning/tooltipPositioningWithArrow.py
pyside_tooltip/positioning/topTooltipPositioning.py
pyside_tooltip/positioning/topTooltipPositioningWithArrow.py
pyside_tooltip/positioning/__init__.py
pyside_tooltip/positioning/bottomTooltipPositioning.py
pyside_tooltip/positioning/bottomTooltipPositioningWithArrow.py
pyside_tooltip/positioning/leftTooltipPositioning.py
pyside_tooltip/positioning/leftTooltipPositioningWithArrow.py
pyside_tooltip/positioning/nullTooltipPositioning.py
pyside_tooltip/positioning/rightTooltipPositioning.py
pyside_tooltip/positioning/rightTooltipPositioningWithArrow.py
pyside_tooltip/positioning/tooltipPositioning.py
pyside_tooltip/positioning/tooltipPositioningWithArrow.py
pyside_tooltip/positioning/topTooltipPositioning.py
pyside_tooltip/positioning/topTooltipPositioningWithArrow.py