Metadata-Version: 1.1
Name: pyside-tooltip
Version: 0.2.1
Summary: Custom tooltip extension for pyside
Home-page: https://github.com/andimarafioti/pyside-tooltip
Author: Andres Marafioti
Author-email: andimarafioti@gmail.com
License: MIT
Platform: UNKNOWN
Classifier: Development Status :: 5 - Production/Stable
Classifier: License :: OSI Approved :: MIT License
Classifier: Programming Language :: Python :: 2.7
Classifier: Environment :: X11 Applications :: Qt
Classifier: Intended Audience :: Developers
